{
    "version": "https://jsonfeed.org/version/1",
    "title": "OMTea App",
    "description": "",
    "home_page_url": "https://www.omtea.app",
    "feed_url": "https://www.omtea.app/feed.json",
    "user_comment": "",
    "author": {
        "name": "OMT"
    },
    "items": [
        {
            "id": "https://www.omtea.app/gudagutaposuto.html",
            "url": "https://www.omtea.app/gudagutaposuto.html",
            "title": "ぐだぐたポスト",
            "summary": "どういうこっちゃかな",
            "content_html": "<p>どういうこっちゃかな</p>",
            "author": {
                "name": "OMT"
            },
            "tags": [
            ],
            "date_published": "2026-04-19T07:58:06+09:00",
            "date_modified": "2026-04-19T07:58:06+09:00"
        },
        {
            "id": "https://www.omtea.app/douiukotutiya.html",
            "url": "https://www.omtea.app/douiukotutiya.html",
            "title": "どういうこっちゃ",
            "author": {
                "name": "OMT"
            },
            "tags": [
            ],
            "date_published": "2026-04-19T07:51:30+09:00",
            "date_modified": "2026-04-19T07:51:30+09:00"
        },
        {
            "id": "https://www.omtea.app/gong-shi-zhong-dayon.html",
            "url": "https://www.omtea.app/gong-shi-zhong-dayon.html",
            "title": "工事中だよん",
            "summary": "under constructer",
            "content_html": "<p>under constructer</p>",
            "author": {
                "name": "OMT"
            },
            "tags": [
            ],
            "date_published": "2026-04-19T06:31:30+09:00",
            "date_modified": "2026-04-19T07:07:26+09:00"
        }
    ]
}
